<xml xmlns="https://developers.google.com/blockly/xml">
  <block type="s4d_login" id="45P$_XXOuPgE9:p},DkW" x="62" y="-328">
    <value name="TOKEN">
      <block type="text" id="S+zQSt3/1%Y%A!4]*4D=">
        <field name="TEXT">Your bot token</field>
      </block>
    </value>
  </block>
  <block type="s4d_on_connected" id=".-MZj+b9k`TARJz_~qg/" x="14" y="74">
    <statement name="STATEMENTS">
      <block type="s4d_forever" id=";offq%J7_FgTygq)@JWV">
        <statement name="STATEMENT">
          <block type="s4d_set_bot_game" id="Bq8jGjNLuyrxQW!yfMHR">
            <field name="OIFD">idle</field>
            <field name="TYPE">LISTENING</field>
            <value name="GAME">
              <block type="text_join" id="!q4;)R!5g1j}!nO)i)qN">
                <mutation items="3"></mutation>
                <value name="ADD0">
                  <block type="text" id="l1scRh%+wn1[~(Q#{F*{">
                    <field name="TEXT">The Count is being </field>
                  </block>
                </value>
                <value name="ADD1">
                  <block type="s4d_bot_server_count" id="bdqeK4H;MmjDm}%=Cy/P"></block>
                </value>
                <value name="ADD2">
                  <block type="text" id="T,D~lzfaVVD3mpC)#PQm">
                    <field name="TEXT"> server(s) at the moment right now</field>
                  </block>
                </value>
              </block>
            </value>
            <next>
              <block type="s4d_set_bot_game" id="M2[~zpy__A~9q]-@x9yf">
                <field name="OIFD">idle</field>
                <field name="TYPE">LISTENING</field>
                <value name="GAME">
                  <block type="text_join" id="Sl(T::_V5(3n7AI,,pwU">
                    <mutation items="3"></mutation>
                    <value name="ADD0">
                      <block type="text" id="_4J%2%!hl1yBS[IqDpbZ">
                        <field name="TEXT">The Latency is being </field>
                      </block>
                    </value>
                    <value name="ADD1">
                      <block type="s4d_bot_ping" id="=YsaEUSE6EWqzIa#Sk4F"></block>
                    </value>
                    <value name="ADD2">
                      <block type="text" id="`zWh-wi9M(=Q[Z{q[b={">
                        <field name="TEXT"> ms at the moment right now</field>
                      </block>
                    </value>
                  </block>
                </value>
                <next>
                  <block type="s4d_set_bot_game" id="49G,uh}AGF1$faA=Vp-,">
                    <field name="OIFD">online</field>
                    <field name="TYPE">PLAYING</field>
                    <value name="GAME">
                      <block type="text_join" id="=nd}9|W]1dI+,UgJ]A|g">
                        <mutation items="3"></mutation>
                        <value name="ADD0">
                          <block type="text" id="-HJWC;E{-`h,AX?6hgNG">
                            <field name="TEXT">The Count is being </field>
                          </block>
                        </value>
                        <value name="ADD1">
                          <block type="s4d_bot_server_count" id="mzZCO?Yuh:4]7`},|MDz"></block>
                        </value>
                        <value name="ADD2">
                          <block type="text" id="kJh_CAzu.|qGLj~v?l,}">
                            <field name="TEXT"> server(s) at the moment right now</field>
                          </block>
                        </value>
                      </block>
                    </value>
                    <next>
                      <block type="s4d_set_bot_game" id="0?YV+pUs$7Ordx2$:pC`">
                        <field name="OIFD">online</field>
                        <field name="TYPE">PLAYING</field>
                        <value name="GAME">
                          <block type="text_join" id="N5)0o_.@%=Jb$tZ3},)b">
                            <mutation items="3"></mutation>
                            <value name="ADD0">
                              <block type="text" id="bPu{NASnu!Bu3.p~?c_)">
                                <field name="TEXT">The Latency is being </field>
                              </block>
                            </value>
                            <value name="ADD1">
                              <block type="s4d_bot_ping" id="N_dSqSftbyoxFa%s8mLV"></block>
                            </value>
                            <value name="ADD2">
                              <block type="text" id="i`[5Y@7g];1r$Sgv86$S">
                                <field name="TEXT"> ms at the moment right now</field>
                              </block>
                            </value>
                          </block>
                        </value>
                        <next>
                          <block type="s4d_set_bot_game" id="}.H0KD{t-??+rC-I4pD`">
                            <field name="OIFD">offline</field>
                            <field name="TYPE">STREAMING</field>
                            <value name="GAME">
                              <block type="text_join" id="ILm?Are,--hFUJqRkmF~">
                                <mutation items="3"></mutation>
                                <value name="ADD0">
                                  <block type="text" id="f#VT=_l25/wcK;qB8E-7">
                                    <field name="TEXT">The Count is being </field>
                                  </block>
                                </value>
                                <value name="ADD1">
                                  <block type="s4d_bot_server_count" id="e6SvH0s@Zpz+v$tr*25r"></block>
                                </value>
                                <value name="ADD2">
                                  <block type="text" id="-Q{8.9TC?pVZeE~Lf/^|">
                                    <field name="TEXT"> server(s) at the moment right now</field>
                                  </block>
                                </value>
                              </block>
                            </value>
                            <next>
                              <block type="s4d_set_bot_game" id="f$S1UtH)|;/OmT;l:v,Y">
                                <field name="OIFD">offline</field>
                                <field name="TYPE">STREAMING</field>
                                <value name="GAME">
                                  <block type="text_join" id=".xXx^NNL=?24xt,cN2~|">
                                    <mutation items="3"></mutation>
                                    <value name="ADD0">
                                      <block type="text" id="+-.vR`1zD9)y(bb[mW(d">
                                        <field name="TEXT">The Latency is being </field>
                                      </block>
                                    </value>
                                    <value name="ADD1">
                                      <block type="s4d_bot_ping" id="7%]ZyE}5D/A6CMI01))D"></block>
                                    </value>
                                    <value name="ADD2">
                                      <block type="text" id="2#$P$G}BlxQ}j^990}5O">
                                        <field name="TEXT"> ms at the moment right now</field>
                                      </block>
                                    </value>
                                  </block>
                                </value>
                                <next>
                                  <block type="s4d_set_bot_game" id="j6UUCo0(Z:@q(rL9?{{u">
                                    <field name="OIFD">dnd</field>
                                    <field name="TYPE">WATCHING</field>
                                    <value name="GAME">
                                      <block type="text_join" id="az0$2_G4BD4A.O#z[xa3">
                                        <mutation items="3"></mutation>
                                        <value name="ADD0">
                                          <block type="text" id="7QPz~Z2^M;SOanbBP^#V">
                                            <field name="TEXT">The Count is being </field>
                                          </block>
                                        </value>
                                        <value name="ADD1">
                                          <block type="s4d_bot_server_count" id="DqK=iNNt!8|+H(px{6]$"></block>
                                        </value>
                                        <value name="ADD2">
                                          <block type="text" id="$JE6wr[T6,e9MaBb6lqM">
                                            <field name="TEXT"> server(s) at the moment right now</field>
                                          </block>
                                        </value>
                                      </block>
                                    </value>
                                    <next>
                                      <block type="s4d_set_bot_game" id="o0Yd]7s/Hsw=k=1|q?CC">
                                        <field name="OIFD">dnd</field>
                                        <field name="TYPE">WATCHING</field>
                                        <value name="GAME">
                                          <block type="text_join" id="fPi1aTY/6t|55nMKF}`?">
                                            <mutation items="3"></mutation>
                                            <value name="ADD0">
                                              <block type="text" id="e_)[5,|?MpaBE9ECvgw^">
                                                <field name="TEXT">The Latency is being </field>
                                              </block>
                                            </value>
                                            <value name="ADD1">
                                              <block type="s4d_bot_ping" id="Yi@QzB6rnAJGv[.EtNIv"></block>
                                            </value>
                                            <value name="ADD2">
                                              <block type="text" id="?*{dGwxU3h2ngZ!:^[Vv">
                                                <field name="TEXT"> ms at the moment right now</field>
                                              </block>
                                            </value>
                                          </block>
                                        </value>
                                      </block>
                                    </next>
                                  </block>
                                </next>
                              </block>
                            </next>
                          </block>
                        </next>
                      </block>
                    </next>
                  </block>
                </next>
              </block>
            </next>
          </block>
        </statement>
      </block>
    </statement>
  </block>
  <block type="s4d_on_message" id=".^s4p(I5^T6;RZl|1z?0" x="15" y="1487">
    <statement name="STATEMENTS">
      <block type="controls_if" id="M.F]$5_t*fq#9|c?E9L+">
        <value name="IF0">
          <block type="logic_compare" id="m$g$^a6wE7xPlcCGlzX4">
            <field name="OP">EQ</field>
            <value name="A">
              <block type="s4d_message_content" id="OHJKrvvf-uGt.TrtBRHH"></block>
            </value>
            <value name="B">
              <block type="text" id="*{^`um,~Sd/0z?0zyhee">
                <field name="TEXT">*teslacommandbuttons</field>
              </block>
            </value>
          </block>
        </value>
        <statement name="DO0">
          <block type="s4d_send_button" id="t+9HvaNCxmnVww0trbQU">
            <value name="CHANNEL">
              <block type="s4d_message_channel" id="6M4WG?(0{l7W%:6/`iiX"></block>
            </value>
            <value name="CONTENT">
              <block type="text" id=",(;1RD%;mMJBBg90$`!k">
                <field name="TEXT">&lt;:icons_connect:875395223512047626&gt; Choose a vehicle:</field>
              </block>
            </value>
            <value name="BUTTON">
              <block type="s4d_button_row" id="YxU!pL`Wm*1B{YXwOquK">
                <statement name="BUTTONS">
                  <block type="s4d_message_row_block" id="hR1!S4Uk93`-;3=0M1~}">
                    <mutation xmlns="http://www.w3.org/1999/xhtml" label="true" emoji="true" custom_id="true"></mutation>
                    <value name="LABEL">
                      <block type="text" id="{UIU2UW+GrB)k,IdU)7+">
                        <field name="TEXT">Tesla Model</field>
                      </block>
                    </value>
                    <value name="EMOJI">
                      <block type="text" id="$?/y.)V+ePfO)1FVRMD=">
                        <field name="TEXT">🇸</field>
                      </block>
                    </value>
                    <value name="CUSTOM_ID">
                      <block type="text" id="N@[~jDJNVCU.(JH2yhuT">
                        <field name="TEXT">§Bfqq5p3V@~rGY}%</field>
                      </block>
                    </value>
                    <next>
                      <block type="s4d_message_row_block" id="csm[VT_nX{:d.L.T:KrV">
                        <mutation xmlns="http://www.w3.org/1999/xhtml" label="true" emoji="true" custom_id="true"></mutation>
                        <value name="LABEL">
                          <block type="text" id="N1:G~f58EB%Ap~heORH`">
                            <field name="TEXT">Tesla Model</field>
                          </block>
                        </value>
                        <value name="EMOJI">
                          <block type="text" id="?%Kw}_XGk?JPtc?GlfK;">
                            <field name="TEXT">3️⃣</field>
                          </block>
                        </value>
                        <value name="CUSTOM_ID">
                          <block type="text" id="E(1zyh-]Zz]Nx~:CTkJ=">
                            <field name="TEXT">#b8Vjta~A:AfFScs</field>
                          </block>
                        </value>
                        <next>
                          <block type="s4d_message_row_block" id="AE(:]30UVkN~l[BOBZmC">
                            <mutation xmlns="http://www.w3.org/1999/xhtml" label="true" emoji="true" custom_id="true"></mutation>
                            <value name="LABEL">
                              <block type="text" id="#qWLD-Cegb(xO*y.O+sb">
                                <field name="TEXT">Tesla Model</field>
                              </block>
                            </value>
                            <value name="EMOJI">
                              <block type="text" id="^)_WSZNg3e3_CLct8?a}">
                                <field name="TEXT">🇽</field>
                              </block>
                            </value>
                            <value name="CUSTOM_ID">
                              <block type="text" id="yZ6HiUNjEI:)ZHtaiH~+">
                                <field name="TEXT">Jg9.du%,pt2fYQW_</field>
                              </block>
                            </value>
                            <next>
                              <block type="s4d_message_row_block" id="Xl`@R0Q[-/az~dKn^aYw">
                                <mutation xmlns="http://www.w3.org/1999/xhtml" label="true" emoji="true" custom_id="true"></mutation>
                                <value name="LABEL">
                                  <block type="text" id="*695)Dtzt@sW5VuTCGq)">
                                    <field name="TEXT">Tesla Model</field>
                                  </block>
                                </value>
                                <value name="EMOJI">
                                  <block type="text" id="%{5s=)Rc-m+_iSQcWi*~">
                                    <field name="TEXT">🇾</field>
                                  </block>
                                </value>
                                <value name="CUSTOM_ID">
                                  <block type="text" id="xw1=y^gDt.G9v3d4v`,{">
                                    <field name="TEXT">t,YB.&amp;&lt;F§-bba_Df</field>
                                  </block>
                                </value>
                              </block>
                            </next>
                          </block>
                        </next>
                      </block>
                    </next>
                  </block>
                </statement>
              </block>
            </value>
            <statement name="STATEMENTS">
              <block type="s4d_on_click" id="Z07K3I@]^Gl+:H`#Q@Fe">
                <value name="MEMBER">
                  <block type="s4d_message_author" id="e@}}*0r$|fJcw_#BG]/{"></block>
                </value>
                <statement name="STATEMENTS">
                  <block type="controls_if" id="5#(W;qKtcm[udflrgb67">
                    <value name="IF0">
                      <block type="logic_compare" id="(qR0^[K@Gp8c^BuW2k05">
                        <field name="OP">EQ</field>
                        <value name="A">
                          <block type="s4d_button_click_id" id="^!dm-dGg{xjNf]YQ3VN%"></block>
                        </value>
                        <value name="B">
                          <block type="text" id="DrvHa/E%xO~U:65+))zF">
                            <field name="TEXT">§Bfqq5p3V@~rGY}%</field>
                          </block>
                        </value>
                      </block>
                    </value>
                    <statement name="DO0">
                      <block type="s4d_button_reply" id="/8rxr!sB^e^RdfrD}m+@">
                        <value name="REPLY">
                          <block type="text" id="kn0Nlq2!MK!EVDU@@fNX">
                            <field name="TEXT">Embeds currently unsupported (Tesla Model S)</field>
                          </block>
                        </value>
                        <value name="TRUEORFALSE">
                          <block type="logic_boolean" id="q].K+#D7xaA6xWZi-4zg">
                            <field name="BOOL">TRUE</field>
                          </block>
                        </value>
                      </block>
                    </statement>
                    <next>
                      <block type="controls_if" id="47ai[JXDO]w4{0@t~K5I">
                        <value name="IF0">
                          <block type="logic_compare" id="![h]^WnR|.vjyll+Hq,%">
                            <field name="OP">EQ</field>
                            <value name="A">
                              <block type="s4d_button_click_id" id="PI[ox-ubNqJ[4vgh(Z8|"></block>
                            </value>
                            <value name="B">
                              <block type="text" id="Z)~(0|[|TpW0C,29*ZF9">
                                <field name="TEXT">#b8Vjta~A:AfFScs</field>
                              </block>
                            </value>
                          </block>
                        </value>
                        <statement name="DO0">
                          <block type="s4d_button_reply" id="D,,-]#K^t{HtWuw_c#EU">
                            <value name="REPLY">
                              <block type="text" id="hOmrN1jHv%M}XRN.n90@">
                                <field name="TEXT">Embeds currently unsupported (Tesla Model S)</field>
                              </block>
                            </value>
                            <value name="TRUEORFALSE">
                              <block type="logic_boolean" id="T@k{IT_P$UINncsLs(n/">
                                <field name="BOOL">TRUE</field>
                              </block>
                            </value>
                          </block>
                        </statement>
                        <next>
                          <block type="controls_if" id="`%8aBnV.S)YoRdwf6G;S">
                            <value name="IF0">
                              <block type="logic_compare" id="+Dk#6PQm|*VXro^YoN.M">
                                <field name="OP">EQ</field>
                                <value name="A">
                                  <block type="s4d_button_click_id" id="c]hRteCi,v%^+apsa[D+"></block>
                                </value>
                                <value name="B">
                                  <block type="text" id="S[.Ma?8WR5zHI|+hdB=J">
                                    <field name="TEXT">Jg9.du%,pt2fYQW_</field>
                                  </block>
                                </value>
                              </block>
                            </value>
                            <statement name="DO0">
                              <block type="s4d_button_reply" id="qZ@czv2k{T4oQOt#GrGU">
                                <value name="REPLY">
                                  <block type="text" id="6BA}lvQTjrHOWrd$li_L">
                                    <field name="TEXT">Embeds currently unsupported (Tesla Model S)</field>
                                  </block>
                                </value>
                                <value name="TRUEORFALSE">
                                  <block type="logic_boolean" id="$sI9zORTr:8^bnz=.~#)">
                                    <field name="BOOL">TRUE</field>
                                  </block>
                                </value>
                              </block>
                            </statement>
                            <next>
                              <block type="controls_if" id="XG}+v[MkYT6f-PCzW+{a">
                                <value name="IF0">
                                  <block type="logic_compare" id=":fg;`OjKz0vMG@kdA+@d">
                                    <field name="OP">EQ</field>
                                    <value name="A">
                                      <block type="s4d_button_click_id" id="v?Rmccdbx]%n7gPPAj3j"></block>
                                    </value>
                                    <value name="B">
                                      <block type="text" id="4QD_j?wU=-M2LbrYo,*I">
                                        <field name="TEXT">t,YB.&amp;&lt;F§-bba_Df</field>
                                      </block>
                                    </value>
                                  </block>
                                </value>
                                <statement name="DO0">
                                  <block type="s4d_button_reply" id="3L.T77CTjMjH_dG=v5CT">
                                    <value name="REPLY">
                                      <block type="text" id="k|Bi6bL/3|o/d,n8q*mZ">
                                        <field name="TEXT">Embeds currently unsupported (Tesla Model S)</field>
                                      </block>
                                    </value>
                                    <value name="TRUEORFALSE">
                                      <block type="logic_boolean" id="Kf*6V[H()6(={~:Gr/dP">
                                        <field name="BOOL">TRUE</field>
                                      </block>
                                    </value>
                                  </block>
                                </statement>
                              </block>
                            </next>
                          </block>
                        </next>
                      </block>
                    </next>
                  </block>
                </statement>
              </block>
            </statement>
          </block>
        </statement>
        <next>
          <block type="controls_if" id="5hWFD#fCO4M$!?`Nr2[J">
            <value name="IF0">
              <block type="logic_compare" id="gQg$7FJtRGo8-j)~A5-p">
                <field name="OP">EQ</field>
                <value name="A">
                  <block type="s4d_message_content" id="9,GQ3t|.Qhk[]N[R%n;i"></block>
                </value>
                <value name="B">
                  <block type="text" id="*MU1(f.Edq2,(Ua9+7]H">
                    <field name="TEXT">*teslacommandmenus</field>
                  </block>
                </value>
              </block>
            </value>
            <statement name="DO0">
              <block type="s4d_send_button" id="eQb^pK~(4Dz@8~GAw{4/">
                <value name="CHANNEL">
                  <block type="s4d_message_channel" id="%Cijg?2^ZlUM![=C$J*s"></block>
                </value>
                <value name="CONTENT">
                  <block type="text" id="*3+*SPg#4`LgL4~O/$US">
                    <field name="TEXT">&lt;:icons_connect:875395223512047626&gt; Choose a vehicle;</field>
                  </block>
                </value>
                <value name="BUTTON">
                  <block type="s4d_button_menu" id="`Dc6j5}2zAkgGH!8jirK">
                    <value name="ID">
                      <block type="text" id="fu]cCvBNM,iTL^Vm%UWX">
                        <field name="TEXT">cWuFf-M2V}sj4VG-</field>
                      </block>
                    </value>
                    <value name="PLACEHOLDER">
                      <block type="text" id=":-f~?()O02vb*[tqw*um">
                        <field name="TEXT">Select a vehicle</field>
                      </block>
                    </value>
                    <statement name="OPTIONS">
                      <block type="s4d_message_menu_block" id="BaFCP@h`9`8_hkH#O7i2">
                        <mutation xmlns="http://www.w3.org/1999/xhtml" label2="true" emoji2="true" custom_id2="true"></mutation>
                        <value name="LABEL2">
                          <block type="text" id="7]i:lVzq1D*IR#n:Ppb6">
                            <field name="TEXT">Tesla Model</field>
                          </block>
                        </value>
                        <value name="EMOJI2">
                          <block type="text" id="lf#fp.l~Q*pfJ*P;zcld">
                            <field name="TEXT">🇸</field>
                          </block>
                        </value>
                        <value name="CUSTOM_ID2">
                          <block type="text" id="^~Z}IaHXlm*iJ{..qGN8">
                            <field name="TEXT">}L6B=uX,Sb$g!85p</field>
                          </block>
                        </value>
                        <next>
                          <block type="s4d_message_menu_block" id="aR@OhJr27]z)zUB-hTd$">
                            <mutation xmlns="http://www.w3.org/1999/xhtml" label2="true" emoji2="true" custom_id2="true"></mutation>
                            <value name="LABEL2">
                              <block type="text" id="/H:^-IT%_+i5+/J,/7TD">
                                <field name="TEXT">Tesla Model</field>
                              </block>
                            </value>
                            <value name="EMOJI2">
                              <block type="text" id="g=RTj3jcCfAl0_(R)~xv">
                                <field name="TEXT">3️⃣</field>
                              </block>
                            </value>
                            <value name="CUSTOM_ID2">
                              <block type="text" id="3C[i^TS@ajlmt74V9@vN">
                                <field name="TEXT">A%dWJdU,3.uP$D,,</field>
                              </block>
                            </value>
                            <next>
                              <block type="s4d_message_menu_block" id="It_}q1B_6Xnkq$lm(#$R">
                                <mutation xmlns="http://www.w3.org/1999/xhtml" label2="true" emoji2="true" custom_id2="true"></mutation>
                                <value name="LABEL2">
                                  <block type="text" id="e^xPZedg^{of{4%5+,(j">
                                    <field name="TEXT">Tesla Model</field>
                                  </block>
                                </value>
                                <value name="EMOJI2">
                                  <block type="text" id=".iSqLPk)D67vthBtr-t|">
                                    <field name="TEXT">🇽</field>
                                  </block>
                                </value>
                                <value name="CUSTOM_ID2">
                                  <block type="text" id="X6#1;fC-rPJZN3%c5cQl">
                                    <field name="TEXT">zv8dh8}jm?pjP+F&gt;</field>
                                  </block>
                                </value>
                                <next>
                                  <block type="s4d_message_menu_block" id="6q^+0~{fDNfus/P;IsZ^">
                                    <mutation xmlns="http://www.w3.org/1999/xhtml" label2="true" emoji2="true" custom_id2="true"></mutation>
                                    <value name="LABEL2">
                                      <block type="text" id="E!wOMzcl^M{:%IAgIwmJ">
                                        <field name="TEXT">Tesla Model</field>
                                      </block>
                                    </value>
                                    <value name="EMOJI2">
                                      <block type="text" id="V4Zet0wH85u!fii^uPHI">
                                        <field name="TEXT">🇾</field>
                                      </block>
                                    </value>
                                    <value name="CUSTOM_ID2">
                                      <block type="text" id="[(v?}+tPuVkMxe9tz1M:">
                                        <field name="TEXT">Y?yRxan!QyY-#m4n</field>
                                      </block>
                                    </value>
                                  </block>
                                </next>
                              </block>
                            </next>
                          </block>
                        </next>
                      </block>
                    </statement>
                  </block>
                </value>
                <statement name="STATEMENTS">
                  <block type="s4d_on_menu_click" id="fCrB+;[/?IKt8|S(isCj">
                    <value name="MEMBER">
                      <block type="s4d_message_author" id="td+mfN@#FYa=oBrypq1w"></block>
                    </value>
                    <statement name="STATEMENTS">
                      <block type="controls_if" id="9}{)r3U`X2lB)-#Z$#+q">
                        <value name="IF0">
                          <block type="logic_compare" id="PgRj~^pR~?rpWfO#2m(/">
                            <field name="OP">EQ</field>
                            <value name="A">
                              <block type="s4d_menu_click_id" id="F=Zg26a}S:[];{av{bY="></block>
                            </value>
                            <value name="B">
                              <block type="text" id="nPS;nbMJqmPez2+;~gMq">
                                <field name="TEXT">cWuFf-M2V}sj4VG-</field>
                              </block>
                            </value>
                          </block>
                        </value>
                        <statement name="DO0">
                          <block type="controls_if" id="up#aCUx-WR#RHu?k^?v!">
                            <value name="IF0">
                              <block type="logic_compare" id="{jGkY!XxuOLe2/EUVXDD">
                                <field name="OP">EQ</field>
                                <value name="A">
                                  <block type="s4d_menu_value" id="M]R0tK0`w;j^Hh|3OO25"></block>
                                </value>
                                <value name="B">
                                  <block type="text" id="n{At41S(K+60Ft1r$)$x">
                                    <field name="TEXT">}L6B=uX,Sb$g!85p</field>
                                  </block>
                                </value>
                              </block>
                            </value>
                            <statement name="DO0">
                              <block type="s4d_button_reply" id="Qz=|i]tMS9bKxPS5:R7f">
                                <value name="REPLY">
                                  <block type="text" id="]ba8$YwWvD8@U;Br]9+{">
                                    <field name="TEXT">Embeds currently unsupported (Tesla Model S)</field>
                                  </block>
                                </value>
                                <value name="TRUEORFALSE">
                                  <block type="logic_boolean" id="G*,kGtq6t%y[i(wYD$n1">
                                    <field name="BOOL">TRUE</field>
                                  </block>
                                </value>
                              </block>
                            </statement>
                            <next>
                              <block type="controls_if" id="0B0mp*:Hmu(0BR}XK{I@">
                                <value name="IF0">
                                  <block type="logic_compare" id="{t-O6Ts:I]MZIf|@s85]">
                                    <field name="OP">EQ</field>
                                    <value name="A">
                                      <block type="s4d_menu_value" id="c9.Bi7m{^)GZ=FtYOlEz"></block>
                                    </value>
                                    <value name="B">
                                      <block type="text" id="{*h|$=st^*@1:Wchxv(u">
                                        <field name="TEXT">A%dWJdU,3.uP$D,,</field>
                                      </block>
                                    </value>
                                  </block>
                                </value>
                                <statement name="DO0">
                                  <block type="s4d_button_reply" id="2_|:i(A5gQ9HZ/cmulW^">
                                    <value name="REPLY">
                                      <block type="text" id="c4LwJ,)Qi}[wfFLzk?1,">
                                        <field name="TEXT">Embeds currently unsupported (Tesla Model S)</field>
                                      </block>
                                    </value>
                                    <value name="TRUEORFALSE">
                                      <block type="logic_boolean" id="P#t*Ia{XRc1Zqp`fwJC[">
                                        <field name="BOOL">TRUE</field>
                                      </block>
                                    </value>
                                  </block>
                                </statement>
                                <next>
                                  <block type="controls_if" id="(v_0oj?,+LVEB]|//`e[">
                                    <value name="IF0">
                                      <block type="logic_compare" id="H0L-Al7Xi)_6h=p1P^BK">
                                        <field name="OP">EQ</field>
                                        <value name="A">
                                          <block type="s4d_menu_value" id="`Oa2fou-txTCrbO_a=Ku"></block>
                                        </value>
                                        <value name="B">
                                          <block type="text" id="/Z6BNy;_e-17v8$tKxQo">
                                            <field name="TEXT">zv8dh8}jm?pjP+F&gt;</field>
                                          </block>
                                        </value>
                                      </block>
                                    </value>
                                    <statement name="DO0">
                                      <block type="s4d_button_reply" id="zJG$iL+}^vz+x-diSf@l">
                                        <value name="REPLY">
                                          <block type="text" id="#-OxdhDxm|1Qq3R*tJ/=">
                                            <field name="TEXT">Embeds currently unsupported (Tesla Model S)</field>
                                          </block>
                                        </value>
                                        <value name="TRUEORFALSE">
                                          <block type="logic_boolean" id="4C@^I@,Gg)~Y,Z:S[E6@">
                                            <field name="BOOL">TRUE</field>
                                          </block>
                                        </value>
                                      </block>
                                    </statement>
                                    <next>
                                      <block type="controls_if" id="PRVPfvF-n044_@ICTsUD">
                                        <value name="IF0">
                                          <block type="logic_compare" id=")uG/+5v2lS@7aXRM2C5G">
                                            <field name="OP">EQ</field>
                                            <value name="A">
                                              <block type="s4d_menu_value" id="wB4[;lE}p|{iFO]-Ij7}"></block>
                                            </value>
                                            <value name="B">
                                              <block type="text" id="lrQGM)o?!h];tPd/T1bp">
                                                <field name="TEXT">Y?yRxan!QyY-#m4n</field>
                                              </block>
                                            </value>
                                          </block>
                                        </value>
                                        <statement name="DO0">
                                          <block type="s4d_button_reply" id="^x,CU$z-Ai?_9-(b-O9e">
                                            <value name="REPLY">
                                              <block type="text" id="^0]eMzz?UKy]4`76l9]0">
                                                <field name="TEXT">Embeds currently unsupported (Tesla Model S)</field>
                                              </block>
                                            </value>
                                            <value name="TRUEORFALSE">
                                              <block type="logic_boolean" id="wFb6U0H6NK4J_98KaiEJ">
                                                <field name="BOOL">TRUE</field>
                                              </block>
                                            </value>
                                          </block>
                                        </statement>
                                      </block>
                                    </next>
                                  </block>
                                </next>
                              </block>
                            </next>
                          </block>
                        </statement>
                      </block>
                    </statement>
                  </block>
                </statement>
              </block>
            </statement>
          </block>
        </next>
      </block>
    </statement>
  </block>
</xml>